oss_lib/__init__.py
oss_lib/config.py
oss_lib/routing.py
oss_lib/templates/routing_map.html
oss_lib-0.1.1.dist-info/DESCRIPTION.rst
oss_lib-0.1.1.dist-info/METADATA
oss_lib-0.1.1.dist-info/RECORD
oss_lib-0.1.1.dist-info/WHEEL
oss_lib-0.1.1.dist-info/metadata.json
oss_lib-0.1.1.dist-info/top_level.txt
